odoo/addons/helpdesk_ticket_board_logistics/CHANGELOG.md
odoo/addons/helpdesk_ticket_board_logistics/README.rst
odoo/addons/helpdesk_ticket_board_logistics/__init__.py
odoo/addons/helpdesk_ticket_board_logistics/__manifest__.py
odoo/addons/helpdesk_ticket_board_logistics/hooks.py
odoo/addons/helpdesk_ticket_board_logistics/data/helpdesk_ticket_team.xml
odoo/addons/helpdesk_ticket_board_logistics/i18n/ca_ES.po
odoo/addons/helpdesk_ticket_board_logistics/i18n/es.po
odoo/addons/helpdesk_ticket_board_logistics/models/__init__.py
odoo/addons/helpdesk_ticket_board_logistics/models/helpdesk_ticket.py
odoo/addons/helpdesk_ticket_board_logistics/models/helpdesk_ticket_team.py
odoo/addons/helpdesk_ticket_board_logistics/static/description/icon.png
odoo/addons/helpdesk_ticket_board_logistics/tests/__init__.py
odoo/addons/helpdesk_ticket_board_logistics/tests/test_helpdesk_ticket.py
odoo/addons/helpdesk_ticket_board_logistics/views/helpdesk_dashboard_view.xml
odoo/addons/helpdesk_ticket_board_logistics/views/helpdesk_ticket_view.xml
odoo12_addon_helpdesk_ticket_board_logistics-12.0.1.0.1.dist-info/METADATA
odoo12_addon_helpdesk_ticket_board_logistics-12.0.1.0.1.dist-info/WHEEL
odoo12_addon_helpdesk_ticket_board_logistics-12.0.1.0.1.dist-info/top_level.txt
odoo12_addon_helpdesk_ticket_board_logistics-12.0.1.0.1.dist-info/RECORD
